qfin/__init__.py
qfin/options.py
qfin/simulations.py
qfin/stochastics.py
qfin-0.1.24.dist-info/LICENSE
qfin-0.1.24.dist-info/METADATA
qfin-0.1.24.dist-info/WHEEL
qfin-0.1.24.dist-info/top_level.txt
qfin-0.1.24.dist-info/RECORD
