Metadata-Version: 2.1
Name: qfin
Version: 0.1.24
Summary: A Python library for mathematical finance.
Author: Roman Paolucci
Author-email: <romanmichaelpaolucci@gmail.com>
License: MIT
Keywords: python,finance
Classifier: Development Status :: 1 - Planning
Classifier: Intended Audience :: Developers
Classifier: Programming Language :: Python :: 3
Classifier: Operating System :: Unix
Classifier: Operating System :: MacOS :: MacOS X
Classifier: Operating System :: Microsoft :: Windows
License-File: LICENSE
Requires-Dist: scipy
Requires-Dist: numpy
